robust_syslog_wrap
