Metadata-Version: 2.2
Name: robust-syslog-wrap
Version: 1.1.0
Summary: A tool to wrap commands and forward standard out and stdin to syslog via TCP
Home-page: https://github.com/talwrii/syslog-wrap
Author: @readwithai
Author-email: talwrii@gmail.com
Classifier: Programming Language :: Python :: 3
Classifier: License :: OSI Approved :: MIT License
Classifier: Operating System :: OS Independent
Requires-Python: >=3.6
License-File: LICENSE
Requires-Dist: asyncio
Dynamic: author
Dynamic: author-email
Dynamic: classifier
Dynamic: description
Dynamic: description-content-type
Dynamic: home-page
Dynamic: requires-dist
Dynamic: requires-python
Dynamic: summary
